CHANGES.rst
CONTRIBUTORS.rst
DEVELOP.rst
LICENSE.GPL
LICENSE.rst
MANIFEST.in
README.rst
constraints.txt
constraints_plone52.txt
requirements.txt
setup.cfg
setup.py
tox.ini
docs/conf.py
docs/index.rst
src/collective/__init__.py
src/collective.anonymouseditpatterns.egg-info/PKG-INFO
src/collective.anonymouseditpatterns.egg-info/SOURCES.txt
src/collective.anonymouseditpatterns.egg-info/dependency_links.txt
src/collective.anonymouseditpatterns.egg-info/entry_points.txt
src/collective.anonymouseditpatterns.egg-info/namespace_packages.txt
src/collective.anonymouseditpatterns.egg-info/not-zip-safe
src/collective.anonymouseditpatterns.egg-info/requires.txt
src/collective.anonymouseditpatterns.egg-info/top_level.txt
src/collective/anonymouseditpatterns/__init__.py
src/collective/anonymouseditpatterns/configure.zcml
src/collective/anonymouseditpatterns/interfaces.py
src/collective/anonymouseditpatterns/permissions.zcml
src/collective/anonymouseditpatterns/setuphandlers.py
src/collective/anonymouseditpatterns/testing.py
src/collective/anonymouseditpatterns/browser/__init__.py
src/collective/anonymouseditpatterns/browser/configure.zcml
src/collective/anonymouseditpatterns/browser/overrides/.gitkeep
src/collective/anonymouseditpatterns/browser/static/.gitkeep
src/collective/anonymouseditpatterns/browser/static/anonymouseditpatterns-compiled.min.css
src/collective/anonymouseditpatterns/browser/static/anonymouseditpatterns-compiled.min.css.map
src/collective/anonymouseditpatterns/browser/static/anonymouseditpatterns-compiled.min.js
src/collective/anonymouseditpatterns/browser/static/anonymouseditpatterns-compiled.min.js.map
src/collective/anonymouseditpatterns/browser/static/css/anonymouseditpatterns.less
src/collective/anonymouseditpatterns/browser/static/js/anonymouseditpatterns-compiled.js
src/collective/anonymouseditpatterns/browser/static/js/anonymouseditpatterns.js
src/collective/anonymouseditpatterns/locales/README.rst
src/collective/anonymouseditpatterns/locales/__init__.py
src/collective/anonymouseditpatterns/locales/collective.anonymouseditpatterns.pot
src/collective/anonymouseditpatterns/locales/update.py
src/collective/anonymouseditpatterns/locales/update.sh
src/collective/anonymouseditpatterns/locales/en/LC_MESSAGES/collective.anonymouseditpatterns.po
src/collective/anonymouseditpatterns/profiles/default/browserlayer.xml
src/collective/anonymouseditpatterns/profiles/default/metadata.xml
