Metadata-Version: 2.1
Name: collective.anonymouseditpatterns
Version: 1.0.1
Summary: An add-on for Plone
Home-page: https://github.com/collective/collective.anonymouseditpatterns
Author: Zest Software
Author-email: info@zestsoftware.nl
License: GPL version 2
Project-URL: PyPI, https://pypi.python.org/pypi/collective.anonymouseditpatterns
Project-URL: Source, https://github.com/collective/collective.anonymouseditpatterns
Project-URL: Tracker, https://github.com/collective/collective.anonymouseditpatterns/issues
Keywords: Python Plone CMS
Platform: UNKNOWN
Classifier: Environment :: Web Environment
Classifier: Framework :: Plone
Classifier: Framework :: Plone :: Addon
Classifier: Framework :: Plone :: 5.2
Classifier: Programming Language :: Python
Classifier: Programming Language :: Python :: 2.7
Classifier: Programming Language :: Python :: 3.7
Classifier: Operating System :: OS Independent
Classifier: License :: OSI Approved :: GNU General Public License v2 (GPLv2)
Provides-Extra: test
